.gitmodules
CMakeLists.txt
LICENSE
MANIFEST.in
README.md
setup.py
cmake/modules/FindCUDA.cmake
cmake/modules/FindCuDNN.cmake
cmake/modules/FindJsonCpp.cmake
cmake/modules/FindMongoDB.cmake
cmake/modules/FindNVML.cmake
cmake/modules/FindPugiXML.cmake
cmake/modules/FindSphinx.cmake
cmake/modules/cotire.cmake
cmake/modules/FindCUDA/make2cmake.cmake
cmake/modules/FindCUDA/parse_cubin.cmake
cmake/modules/FindCUDA/run_nvcc.cmake
cmake/modules/FindCUDA/select_compute_arch.cmake
exec/n2d2.cpp
include/Adversarial.hpp
include/CEnvironment.hpp
include/CEnvironment_CUDA.hpp
include/CEnvironment_CUDA_kernels.hpp
include/CMonitor.hpp
include/CMonitor_CUDA.hpp
include/CMonitor_CUDA_kernels.hpp
include/CublasUtils.hpp
include/CudaContext.hpp
include/CudaUtils.hpp
include/DeepNet.hpp
include/DeepNetQuantization.hpp
include/DrawNet.hpp
include/FloatT.hpp
include/GradientCheck.hpp
include/HeteroStimuliProvider.hpp
include/Histogram.hpp
include/N2D2.hpp
include/Precompiled.hpp
include/RangeStats.hpp
include/Scaling.hpp
include/ScalingMode.hpp
include/Scaling_CUDA_Kernels.hpp
include/Scaling_Kernels.hpp
include/Sound.hpp
include/StimuliData.hpp
include/StimuliProvider.hpp
include/Activation/Activation.hpp
include/Activation/Activation_CUDA_Kernels.hpp
include/Activation/LinearActivation.hpp
include/Activation/LinearActivation_Frame.hpp
include/Activation/LinearActivation_Frame_CUDA.hpp
include/Activation/LogisticActivation.hpp
include/Activation/LogisticActivation_Frame.hpp
include/Activation/LogisticActivation_Frame_CUDA.hpp
include/Activation/RectifierActivation.hpp
include/Activation/RectifierActivation_Frame.hpp
include/Activation/RectifierActivation_Frame_CUDA.hpp
include/Activation/SaturationActivation.hpp
include/Activation/SaturationActivation_Frame.hpp
include/Activation/SaturationActivation_Frame_CUDA.hpp
include/Activation/SoftplusActivation.hpp
include/Activation/SoftplusActivation_Frame.hpp
include/Activation/SoftplusActivation_Frame_CUDA.hpp
n2d2.egg-info/PKG-INFO
n2d2.egg-info/SOURCES.txt
n2d2.egg-info/dependency_links.txt
n2d2.egg-info/top_level.txt
